wappstorest/__init__.py
wappstorest/wappsto_service_builder.py
wappstorest/wappstorest.py
wappstorest/wappstows.py
wappstorest/core/__init__.py
wappstorest/core/exceptions.py
wappstorest/core/utils.py
wappstorest/path/WappstoPath.py
wappstorest/path/__init__.py
wappstorest/path/path_helpers.py
wappstorest/path/path_objs/__init__.py
wappstorest/path/path_objs/acl.py
wappstorest/path/path_objs/device.py
wappstorest/path/path_objs/network.py
wappstorest/path/path_objs/session.py
wappstorest/path/path_objs/state.py
wappstorest/path/path_objs/user.py
wappstorest/path/path_objs/value.py
wappstorest/schemas/WappstoCreateSchema.py
wappstorest/schemas/WappstoResponseSchema.py
wappstorest/schemas/WappstoSchema.py
wappstorest/schemas/WappstoUpdateSchema.py
wappstorest/schemas/__init__.py
wappstorest/schemas/base.py
wappstorest/schemas/id_list.py
wappstorest/schemas/websocket_schema.py
wappstorest/schemas/create/__init__.py
wappstorest/schemas/create/acl.py
wappstorest/schemas/create/add_not_owned.py
wappstorest/schemas/create/admin_feature.py
wappstorest/schemas/create/alert.py
wappstorest/schemas/create/analytics.py
wappstorest/schemas/create/analytics_model.py
wappstorest/schemas/create/application.py
wappstorest/schemas/create/application_product.py
wappstorest/schemas/create/azure.py
wappstorest/schemas/create/bus_stream.py
wappstorest/schemas/create/cockroach.py
wappstorest/schemas/create/console.py
wappstorest/schemas/create/couchbase.py
wappstorest/schemas/create/creator.py
wappstorest/schemas/create/customer.py
wappstorest/schemas/create/customer_invoice.py
wappstorest/schemas/create/dashboard.py
wappstorest/schemas/create/data.py
wappstorest/schemas/create/email_draft.py
wappstorest/schemas/create/email_send.py
wappstorest/schemas/create/email_translation.py
wappstorest/schemas/create/eventlog.py
wappstorest/schemas/create/expected_state.py
wappstorest/schemas/create/extsync.py
wappstorest/schemas/create/extsync_response.py
wappstorest/schemas/create/file.py
wappstorest-0.1.0.dist-info/LICENSE
wappstorest-0.1.0.dist-info/METADATA
wappstorest-0.1.0.dist-info/WHEEL
wappstorest-0.1.0.dist-info/top_level.txt
wappstorest-0.1.0.dist-info/RECORD
