Metadata-Version: 2.1
Name: wappstorest
Version: 0.1.0
Summary: Simple Wappsto Python user-interface to Wappsto Rest
Home-page: https://github.com/Wappsto/python-wappsto-rest
Author: Seluxit A/S
Author-email: support@seluxit.com
License: Apache-2.0
Classifier: Programming Language :: Python :: 3
Classifier: Operating System :: OS Independent
Requires-Python: >=3.9.0
License-File: LICENSE
Requires-Dist: pydantic (==1.10.12)
Requires-Dist: httpx (>=0.23.0)
Requires-Dist: websocket-client (>=0.59.0)
Requires-Dist: rich (>=12.0.0)
